{"items":[{"key":"cutscene_camera_brodys_race","value":"npc_brodys_race"},{"key":"ui_notification_02","value":"Global"},{"key":"pg_02_fourcrows_card_select","value":"pg_cityfera"},{"key":"mus_cityfera_lounge_ff","value":"city_fera_lounge_ff"},{"key":"mus_quest_follow_footsteps","value":"twiggle_p_i"},{"key":"harv_swampbat_idle","value":"world_s01e01"},{"key":"ui_slider","value":"Global"},{"key":"sfx_magic_staff_lp","value":"quest_magic_staff_lp"},{"key":"cg_m3_puzzle_piece_select","value":"cg_04_match_3"},{"key":"cg_m3_game_lose","value":"cg_04_match_3"},{"key":"cutscene_camera","value":"global_cutscenes"},{"key":"mus_critter_stingers","value":"world_blood_tundra"},{"key":"boundary_respawn","value":"Global"},{"key":"sfx_quest_brodys_race_fail","value":"npc_brodys_race"},{"key":"cg_m3_select_bird","value":"cg_04_match_3"},{"key":"ui_private_message","value":"Global"},{"key":"cg_btn_settings","value":"global_cg"},{"key":"ui_selfie_btn_toggle_checkmark","value":"Global"},{"key":"qge_picklock_stinger_next_level","value":"qge_picklock"},{"key":"pg_02_fourcrows_crow_banished","value":"pg_cityfera"},{"key":"tradersport_pools","value":"world_traders_port"},{"key":"cooking_bubble_lp","value":"cooking_pot_lp"},{"key":"cg_hex_tile_insert_03","value":"cg_01_whatthehex"},{"key":"quest_cannon_twiggle_found","value":"cannon_countdown"},{"key":"npc_cinder_spawn","value":"world_expanse_quest_01"},{"key":"quest_poofy_poachers_poofy","value":"poofy_poachers"},{"key":"sanc_kino_action_figure","value":"sanc_kino_action_figure"},{"key":"mus_npc_brodys_pre_race","value":"npc_brodys_race"},{"key":"ui_map_zoom_out","value":"Global"},{"key":"cg_m3_egg_spawn","value":"cg_04_match_3"},{"key":"cg_hex_tile_insert_01","value":"cg_01_whatthehex"},{"key":"cg_folly_station_paint","value":"cg_02_builders_folly"},{"key":"cg_folly_stinger_points","value":"cg_02_builders_folly"},{"key":"sanctuary_shattered_bay","value":"mus_sanctuary_shattered_bay"},{"key":"ava_teleport_away_arrive","value":"Global"},{"key":"floating_rocks_lp","value":"global_expanse"},{"key":"ui_decal_item","value":"Global"},{"key":"pg_04_moon_crystal_token_start","value":"pg_shattered_bay"},{"key":"expanse_birds_take_off","value":"world_expanse_forest"},{"key":"cg_m3_special_order_spawn","value":"cg_04_match_3"},{"key":"vox_latchkey","value":"vox_latchkey"},{"key":"ui_revert","value":"Global"},{"key":"harv_shimmer_grass","value":"global_harvest"},{"key":"cg_folly_tile_placed","value":"cg_02_builders_folly"},{"key":"pg_03_m&f_dicecup_reveal_moth","value":"pg_shattered_bay"},{"key":"mus_npc_quest_witches","value":"hocus_pocus"},{"key":"cg_folly_station_rotate","value":"cg_02_builders_folly"},{"key":"sfx_basic_lamp_on_off","value":"sfx_basic_lamp"},{"key":"rs01_camera_zoom_in","value":"reality_show_01"},{"key":"expanse_birds_in_flight","value":"world_expanse_forest"},{"key":"mus_login_creation","value":"login_account_creation"},{"key":"harv_fisheggs_idle_lp","value":"world_expanse_forest"},{"key":"forestsocial_river_lp","value":"world_expanse_forest"},{"key":"npc_mm_move","value":"world_s01e01"},{"key":"vox_twiggla","value":"vox_twiggla"},{"key":"qge_window_open","value":"qge_picklock"},{"key":"mus_shattered_bay_furnitureshop","value":"shattered_bay_furnitureshop"},{"key":"ava_phoenix_sprint_forward","value":"ava_phoenix"},{"key":"boundary_camera_fade_in","value":"Global"},{"key":"harv_lanternberry_death","value":"world_s01e01"},{"key":"ui_sidebar_poly","value":"Global"},{"key":"ava_senri_emotes","value":"ava_senri"},{"key":"ava_wings_soft","value":"ava_wings_soft"},{"key":"inspiration_combination_fail","value":"Global"},{"key":"ui_btn_inspiration_select_02","value":"Global"},{"key":"mus_menu_default","value":"Global"},{"key":"bloodtundra_blizzard_lp","value":"world_blood_tundra"},{"key":"qge_picklock_life_lost","value":"qge_picklock"},{"key":"harv_sky_chest_idle","value":"global_harvest"},{"key":"harv_rubyfish_move","value":"harv_rubyfish"},{"key":"quest_snowbold_counter_special","value":"toboggan_run"},{"key":"popup_collect_marbles","value":"Global"},{"key":"sanc_balloon_arch","value":"sanc_balloon_arch"},{"key":"sfx_paint_shaking","value":"treehouse_of_hope"},{"key":"ui_dye_found","value":"Global"},{"key":"vox_kobold_kid_trot","value":"vox_kobold_kid_trot"},{"key":"ui_dye_deselect","value":"Global"},{"key":"harv_blooderfly","value":"global_harvest"},{"key":"mus_cityfera_main","value":"world_city_fera"},{"key":"ui_full_view","value":"Global"},{"key":"cg_m3_booster_spawn","value":"cg_04_match_3"},{"key":"sanc_window_wraith","value":"sanc_window_wraith"},{"key":"onboarding_harv_crystal_shoot","value":"onboarding_tutorial"},{"key":"sunkenthicket_waterfall_lrge","value":"world_sunken_thicket"},{"key":"ui_btn_next","value":"Global"},{"key":"sfx_orb_wood_lp","value":"global_expanse"},{"key":"mus_npc_valkeri_note","value":"mus_npc_valkeri_note"},{"key":"swamp_dragon_waterfall_lp","value":"world_s01e01"},{"key":"sfx_twiggle_run","value":"vox_twiggles"},{"key":"ava_kirin_emotes","value":"ava_kirin"},{"key":"cg_dye_collision_ball_blue","value":"cg_03_doordye"},{"key":"cg_dye_beetle_move","value":"cg_03_doordye"},{"key":"cutscene_vermin","value":"lost_and_found"},{"key":"npc_latchkey_uncrafting_disconnect_reconnect","value":"sunken_thicket_uncrafting"},{"key":"qge_chest_lid_open","value":"qge_picklock"},{"key":"ui_charm_item","value":"Global"},{"key":"cg_folly_twiggle_cheer_01","value":"cg_02_builders_folly"},{"key":"quest_broom_sweep","value":"hocus_pocus"},{"key":"vox_vermin","value":"vox_vermin"},{"key":"wpn_spear_pierce_mm","value":"wpn_spear"},{"key":"ui_notification_01","value":"Global"},{"key":"mus_cindernoct_sunkenthicket","value":"world_sunken_thicket"},{"key":"mus_quest_poofy_johannes_song","value":"poofy_poachers"},{"key":"ui_sanc_btn_edit","value":"sanctuary_fera"},{"key":"amb_firefly_shimmer_lp","value":"global_expanse"},{"key":"cg_folly_stinger_reward","value":"cg_02_builders_folly"},{"key":"cg_m3_meter_fill","value":"cg_04_match_3"},{"key":"quest_sfx_paper","value":"a_novel_romance"},{"key":"ui_enigma_btn_select","value":"Global"},{"key":"npc_mm_capture","value":"world_s01e01"},{"key":"sfx_magic_wand_pickup","value":"strange_magic"},{"key":"bloodtundra_ghostship_creaks","value":"world_blood_tundra"},{"key":"mus_npc_musique_marmite","value":"mus_npc_musique_marmite"},{"key":"sfx_dynamite_placed","value":"lost_shoes"},{"key":"eg_rockflipping_camera_cut","value":"eg_rockflipping"},{"key":"cg_hex_tile_error","value":"cg_01_whatthehex"},{"key":"cg_hex_meter_miasma","value":"cg_01_whatthehex"},{"key":"pg_02_fourcrows_tree_dematerialize","value":"pg_cityfera"},{"key":"cg_btn_tutorial","value":"global_cg"},{"key":"pg_01_duel_dice_single_pickup","value":"pg_cityfera"},{"key":"mus_npc_valkeri","value":"mus_npc_valkeri"},{"key":"quest_evil_pumpkin_explo","value":"garden_of_evil"},{"key":"harv_sky_jelly_death","value":"global_harvest"},{"key":"cg_folly_btn_level_select","value":"cg_02_builders_folly"},{"key":"ui_btn_battle_pass_purchase","value":"Global"},{"key":"harv_bloodsnake_idle_lp","value":"world_blood_tundra"},{"key":"mus_sticky_situation_tension","value":"world_s01e01"},{"key":"ava_fae_sleep","value":"ava_fae"},{"key":"cg_folly_twiggle_sparkle","value":"cg_02_builders_folly"},{"key":"ui_dye_craft","value":"Global"},{"key":"ui_popup_main","value":"Global"},{"key":"sfx_tapping_bucket_tree","value":"world_blood_tundra"},{"key":"tradersport_wind","value":"world_traders_port"},{"key":"mus_npc_kobold_white","value":"mus_npc_kobold_white"},{"key":"mus_shop_clothing","value":"Global"},{"key":"sanctuary_woodland_cottage_interior","value":"mus_sanctuary_woodland_cottage"},{"key":"expanse_rain_light_lp","value":"global_expanse"},{"key":"mus_daily_spear_it_tension_test","value":"mus_daily_spear_it"},{"key":"quest_harv_plant_fog_lp","value":"twixt_the_vapors"},{"key":"ava_kirin_jump","value":"ava_kirin"},{"key":"pg_01_duel_dice_drop_slide_release","value":"pg_cityfera"},{"key":"sfx_twiggle_walk","value":"vox_twiggles"},{"key":"cg_folly_stinger_delivered_02","value":"cg_02_builders_folly"},{"key":"ava_shinigami_idle_break_02","value":"ava_shinigami"},{"key":"cg_m3_rainbow_sparkle","value":"cg_04_match_3"},{"key":"harv_rock_harvested","value":"global_harvest"},{"key":"cg_hex_meter_flame","value":"cg_01_whatthehex"},{"key":"ui_quest_tab_open","value":"Global"},{"key":"cg_btn_play","value":"global_cg"},{"key":"onboarding_btn_skip","value":"onboarding_tutorial"},{"key":"rs01_vox_queen_stingers_delilah","value":"reality_show_01"},{"key":"ava_glide_freefall","value":"ava_glide_lp"},{"key":"inspirations_bubble_stream_lp","value":"world_expanse_forest"},{"key":"ava_wings_full","value":"ava_wings_full"},{"key":"quest_boomers_cutscene_stingers","value":"global_cutscenes"},{"key":"ui_uncrafting_shop_btn_craft","value":"Global"},{"key":"bloodtundra_waterfall_sm","value":"world_blood_tundra"},{"key":"ui_btn_play","value":"Global"},{"key":"qge_treasure_coins","value":"qge_picklock"},{"key":"vox_valkeri_cael","value":"vox_valkeri_cael"},{"key":"sanc_carnivorous_larry_fire","value":"sanc_carnivorous_larry"},{"key":"sanc_fire_spits_lp","value":"sanc_fire_spits"},{"key":"boundary_collision","value":"Global"},{"key":"sanc_cottage_wind","value":"sanctuary_ui"},{"key":"sfx_marmite_active_lp","value":"sfx_marmite_active_lp"},{"key":"ui_appform_x","value":"login_account_creation"},{"key":"ui_xp_meter_diamond_single","value":"Global"},{"key":"cg_m3_new_bird_drop","value":"cg_04_match_3"},{"key":"tradersport_ocean_lp","value":"world_traders_port"},{"key":"ui_btn_no","value":"Global"},{"key":"ui_btn_lets_go","value":"login_account_creation"},{"key":"onboarding_player_spark","value":"onboarding_tutorial"},{"key":"harv_sky_jelly_spawn","value":"global_harvest"},{"key":"ui_sanc_btn_decorate","value":"sanctuary_fera"},{"key":"mus_npc_twiggles","value":"mus_npc_twiggle"},{"key":"sfx_inspiration_candle_off","value":"Global"},{"key":"cg_hex_tile_mushroom_bounce","value":"cg_01_whatthehex"},{"key":"sanc_basic_candle_lp","value":"sfx_basic_candle"},{"key":"ava_jackalope_breath_run_test","value":"ava_jackalope"},{"key":"enigma_stinger","value":"Global"},{"key":"ava_werewolf_breath_idle","value":"ava_werewolf"},{"key":"qge_picklock_stab_04","value":"qge_picklock"},{"key":"inspirations_twiggle_lp","value":"world_blood_tundra"},{"key":"pg_01_duel_attack","value":"pg_cityfera"},{"key":"amb_birds_in_flight","value":"amb_birds_in_flight"},{"key":"sfx_statue_restored","value":"fountain_fix"},{"key":"mus_quest_poofy_johannes_snapshot","value":"poofy_poachers"},{"key":"sanc_item_rotate","value":"Global"},{"key":"quest_broom_laughter","value":"hocus_pocus"},{"key":"harv_blooddew_back_move","value":"world_blood_tundra"},{"key":"amb_torch","value":"amb_torch"},{"key":"ava_footsteps","value":"Global"},{"key":"harv_death_crystalback","value":"world_s01e01"},{"key":"sfx_feralamp_candle_on","value":"sanctuary_ui"},{"key":"sanc_fountain_hot_spring","value":"sanc_fountain_hot_springs"},{"key":"pg_01_duel_crystals_zipping","value":"pg_cityfera"},{"key":"cg_dye_collision_ball_energy","value":"cg_03_doordye"},{"key":"bloodtundra_waterfall_blood","value":"world_blood_tundra"},{"key":"forestsocial_pool","value":"world_expanse_forest"},{"key":"mus_npc_komodori","value":"mus_npc_komodori"},{"key":"mus_daily_teeter_fishing","value":"daily_quest_teeter"},{"key":"npc_mm_mud_projectile_lp","value":"world_s01e01"},{"key":"vox_kobolds_low","value":"vox_kobolds_low"},{"key":"ui_customization_day","value":"Global"},{"key":"ui_appform_privacy&terms","value":"Global"},{"key":"cg_folly_twiggle_spawn","value":"cg_02_builders_folly"},{"key":"splash_screen_ducks_sfx","value":"splash_screen_ducks_sfx"},{"key":"quest_item_collected","value":"Global"},{"key":"ava_kirin_breath_idle","value":"ava_kirin"},{"key":"ui_sanc_btn_build","value":"sanctuary_fera"},{"key":"quest_comic_boom_final_shot","value":"finders_keepers"},{"key":"mus_cindernoct_cityfera","value":"world_city_fera"},{"key":"mus_sunken_thicket_uncraftingshop","value":"sunken_thicket_uncrafting"},{"key":"sfx_magic_wand_appear","value":"strange_magic"},{"key":"maze_spawn","value":"world_expanse_quest_01"},{"key":"totem_seg_01","value":"world_expanse_quest_01"},{"key":"sanctuary_cottage_interior","value":"mus_sanctuary_cottage"},{"key":"quest_updated","value":"Global"},{"key":"cg_dye_btn_level_select","value":"cg_03_doordye"},{"key":"ui_btn_iap_purchase","value":"Global"},{"key":"fer_decreeboard_amb_lp","value":"Global"},{"key":"npc_kino_cape","value":"npc_kino_cape"},{"key":"quest_complete","value":"Global"},{"key":"portal_orange","value":"Global"},{"key":"sfx_cutscene_stingers_statue_repair","value":"fountain_fix"},{"key":"cg_hex_tile_special_select","value":"cg_01_whatthehex"},{"key":"quest_vermin_whistle_marker","value":"lost_and_found"},{"key":"ava_dragon_breath_idle","value":"ava_dragon"},{"key":"amb_frost_fete_snowpuff","value":"world_city_fera"},{"key":"mus_twiggle_pear_house","value":"mus_twiggle_pear_house"},{"key":"ui_btn_settings","value":"Global"},{"key":"cg_folly_twiggle_cheer_02","value":"cg_02_builders_folly"},{"key":"npc_latchkey_orb_lp","value":"sunken_thicket_uncrafting"},{"key":"ui_e_hold","value":"Global"},{"key":"bloodtundra_droplets","value":"world_blood_tundra"},{"key":"ui_btn_toggle","value":"Global"},{"key":"eg_rockflipping_gold_sparkle","value":"eg_rockflipping"},{"key":"sfx_stingray_lake_water_splash","value":"world_s01e01"},{"key":"cg_m3_meter_nest_fill","value":"cg_04_match_3"},{"key":"vox_andrulienne","value":"vox_andrulienne"},{"key":"ui_btn_player_info","value":"Global"},{"key":"vox_valkeri_kid","value":"vox_valkeri_kid"},{"key":"pg_03_m&f_crystalpulse_ring","value":"pg_shattered_bay"},{"key":"tradersport_crystal_lrge","value":"world_traders_port"},{"key":"harv_sky_chest_hit","value":"global_harvest"},{"key":"forestsocial_fountain","value":"world_expanse_forest"},{"key":"vox_komodori_kid","value":"vox_komodori_kid"},{"key":"ava_phoenix_run_forward","value":"ava_phoenix"},{"key":"harv_tool_net","value":"Global"},{"key":"harv_cinderfish_idle","value":"world_expanse_forest"},{"key":"vox_valkeri_idle_break","value":"vox_valkeri_high"},{"key":"quest_poofy_distraction","value":"poofy_poachers"},{"key":"pg_03_m&f_dicecup_scoop","value":"pg_shattered_bay"},{"key":"harv_preymantis_jump_move","value":"world_s01e01"},{"key":"harv_bloodsnake_move","value":"world_blood_tundra"},{"key":"pg_03_m&f_dicecup_reveal_flame","value":"pg_shattered_bay"},{"key":"ui_trade_btn_invite","value":"Global"},{"key":"wayfarer_01","value":"world_expanse_quest_01"},{"key":"boundary_camera_fade_out","value":"Global"},{"key":"pg_02_fourcrows_tree_materialize_lp","value":"pg_cityfera"},{"key":"quest_sfx_twiggle_steps","value":"cannon_countdown"},{"key":"mus_sunken_thicket_main","value":"world_sunken_thicket"},{"key":"pg_02_fourcrows_crow_caw","value":"pg_cityfera"},{"key":"quest_waypoint_select","value":"global_expanse"},{"key":"ava_glide_lp","value":"ava_glide_lp"},{"key":"cg_03_mus_doordye","value":"cg_03_doordye"},{"key":"cg_dye_collision_ball_leaf","value":"cg_03_doordye"},{"key":"ava_fae_sleep_wings_flap","value":"ava_fae"},{"key":"tradersport_waterfall_lrge","value":"world_traders_port"},{"key":"mus_iap_battle_pass_shop","value":"Global"},{"key":"cinder_01","value":"world_expanse_quest_01"},{"key":"ui_sanc_btn_interior","value":"sanctuary_fera"},{"key":"mus_npc_striker","value":"mus_npc_striker"},{"key":"sfx_quest_high_pitched_whine","value":"old_wounds"},{"key":"npc_picken","value":"picken_pick_up"},{"key":"mus_npc_bellamy_outpost","value":"mus_npc_bellamy_outpost"},{"key":"zombold_moan","value":"snowman_explo"},{"key":"sfx_stinger_seagulls_kite","value":"chaos_from_above"},{"key":"ui_btn_highlight","value":"Global"},{"key":"cg_hex_x_points","value":"cg_01_whatthehex"},{"key":"harv_sinew_husk_idle","value":"global_harvest"},{"key":"ava_kirin_run","value":"ava_kirin"},{"key":"ui_emoticon_btn_select","value":"Global"},{"key":"sanctuary_rose_house_interior","value":"mus_sanctuary_rose_house"},{"key":"rs01_aradia_stinger_embarrassed","value":"reality_show_01"},{"key":"sfx_cutscene_stinger_cursed_bucket","value":"captain_cluck"},{"key":"cg_dye_cauldron_active","value":"cg_03_doordye"},{"key":"ui_appform_checkmark","value":"login_account_creation"},{"key":"cg_button_close","value":"global_cg"},{"key":"vox_kobolds_low_trot","value":"vox_kobolds_low_trot"},{"key":"harv_tool_scythe","value":"Global"},{"key":"quest_sfx_cannon_fire","value":"cannon_countdown"},{"key":"cg_hex_tile_wiggle","value":"cg_01_whatthehex"},{"key":"ava_senri_breath_idle","value":"ava_senri"},{"key":"cg_folly_twiggle_steps","value":"cg_02_builders_folly"},{"key":"ui_btn_bellamy_purchase","value":"world_sunken_thicket"},{"key":"harv_nettlefish","value":"world_expanse_forest"},{"key":"eg_rockflipping_rock_shatter","value":"eg_rockflipping"},{"key":"sfx_door_knock","value":"sfx_door_knock"},{"key":"vox_myrefolk_high","value":"vox_myrefolk_high"},{"key":"npc_wayfarer_stand","value":"world_expanse_quest_01"},{"key":"harv_leering_mangrove","value":"world_s01e01"},{"key":"harv_skulltulip_mask_death","value":"world_s01e01"},{"key":"npc_valkeri_lute_mus_silence","value":"world_traders_port"},{"key":"harv_skull_tulip","value":"world_s01e01"},{"key":"cg_folly_btn_reset","value":"cg_02_builders_folly"},{"key":"ava_jackalope_emotes","value":"ava_jackalope"},{"key":"ava_jackalope_breath_idle","value":"ava_jackalope"},{"key":"ava_swim_dive","value":"Global"},{"key":"ava_fae_emotes","value":"ava_fae"},{"key":"mus_npc_karens_theme","value":"mus_npc_karens_theme"},{"key":"eg_digging_success","value":"eg_dig_up"},{"key":"cg_folly_btn_goalslist","value":"cg_02_builders_folly"},{"key":"quest_snowbold_death","value":"toboggan_run"},{"key":"pg_04_moon_domino_placed","value":"pg_shattered_bay"},{"key":"sanc_garden_hose_toggle_on","value":"sanc_garden_hose"},{"key":"quest_magic_spawn","value":"quest_magic_spawn"},{"key":"cg_m3_puzzle_piece_placed","value":"cg_04_match_3"},{"key":"mus_mugmyre_marsh_title","value":"world_s01e01"},{"key":"blocker_crystals_red","value":"Global"},{"key":"cg_dye_stinger_result_screen","value":"cg_03_doordye"},{"key":"pg_02_fourcrows_crow_caw_death","value":"pg_cityfera"},{"key":"vox_komodori_shady","value":"vox_komodori_shady"},{"key":"cutscene_camera_question","value":"global_cutscenes"},{"key":"door_cottage_close","value":"sanctuary_ui"},{"key":"vox_historian","value":"vox_historian"},{"key":"wpn_light_spear_block","value":"wpn_spear"},{"key":"mus_inspiration","value":"Global"},{"key":"sanc_crickets","value":"mus_sanctuary_cityfera"},{"key":"mus_quest_johannes_snapshot","value":"poofy_poachers"},{"key":"ava_shop_duck_avatar","value":"Global"},{"key":"ui_apply","value":"Global"},{"key":"quest_evil_pumpkin_emerge","value":"garden_of_evil"},{"key":"mus_world_map_stage","value":"Global"},{"key":"sanc_clock_lp","value":"sanc_clock_gears_lp"},{"key":"mus_npc_troop_theme","value":"mus_npc_troop_theme"},{"key":"pg_01_duel_dice_rotate_lower","value":"pg_cityfera"},{"key":"harv_lucidinfection","value":"world_expanse_forest"},{"key":"mus_cityfera_lounge_cn","value":"city_fera_lounge_cn"},{"key":"quest_toboggan_fail","value":"toboggan_run"},{"key":"ui_appform_questionmark","value":"login_account_creation"},{"key":"ui_uncrafting_btn_select","value":"Global"},{"key":"mus_cityfera_lounge","value":"city_fera_lounge"},{"key":"rs01_aradia_stinger_excited","value":"reality_show_01"},{"key":"sfx_player_impact","value":"global_expanse"},{"key":"rs01_mus_queens_reality_show","value":"reality_show_01"},{"key":"mus_npc_the_confused","value":"mus_npc_the_confused"},{"key":"onboarding_highlighter_ding","value":"onboarding_tutorial"},{"key":"mus_npc_kid","value":"mus_npc_kid"},{"key":"ui_friend_add","value":"Global"},{"key":"sanc_fountain_mud","value":"sanc_fountain_mud"},{"key":"npc_wayfarer_lean","value":"world_expanse_quest_01"},{"key":"sanc_amb_haunted","value":"mus_sanctuary_haunted"},{"key":"cg_hex_icon_lift","value":"cg_01_whatthehex"},{"key":"cg_btn_choose","value":"global_cg"},{"key":"ui_trade_btn_item_add","value":"Global"},{"key":"sfx_collected_bones","value":"sfx_collected_bones"},{"key":"cg_04_mus_match3_splash_lp","value":"cg_04_match_3"},{"key":"cg_01_mus_whatthehex","value":"cg_01_whatthehex"},{"key":"pg_01_duel_empty","value":"pg_cityfera"},{"key":"ui_btn_battle_pass_more_info","value":"Global"},{"key":"rs01_delilah_stinger_love","value":"reality_show_01"},{"key":"npc_stinger_hats_big_day_scram","value":"hats_day_out"},{"key":"cg_m3_puzzle_portrait_select","value":"cg_04_match_3"},{"key":"cg_m3_special_order_added","value":"cg_04_match_3"},{"key":"npc_stinger_the_confused","value":"world_blood_tundra"},{"key":"ui_trade_btn_accept","value":"Global"},{"key":"pg_01_duel_btn_reroll","value":"pg_cityfera"},{"key":"mus_qge_picklock_gold","value":"qge_picklock"},{"key":"pg_02_fourcrows_branch_crackle","value":"pg_cityfera"},{"key":"ui_likes_popup","value":"Global"},{"key":"ui_btn_okay","value":"Global"},{"key":"mus_npc_lonely","value":"mus_npc_lonely"},{"key":"cg_btn_mix","value":"cg_03_doordye"},{"key":"pg_03_duel_dice_group_drop_table","value":"pg_cityfera"},{"key":"mus_npc_serial_chiller_stinger","value":"world_blood_tundra"},{"key":"cutscene_camera_whoosh","value":"global_cutscenes"},{"key":"onboarding_player_spark_lp","value":"onboarding_tutorial"},{"key":"harv_jellycap","value":"world_s01e01"},{"key":"ui_interaction_prompt","value":"Global"},{"key":"mus_npc_twiggle_build","value":"mus_npc_twiggle"},{"key":"npc_mm_idle","value":"world_s01e01"},{"key":"cutscene_finders_keepers","value":"finders_keepers"},{"key":"sanc_fishbowl_bubbles_lp","value":"sanc_fishbowl_bubbles_lp"},{"key":"ui_charm_place","value":"Global"},{"key":"cg_m3_moves_left","value":"cg_04_match_3"},{"key":"ava_kitsune_breath_run","value":"Global"},{"key":"cg_m3_stinger_bird_regular","value":"cg_04_match_3"},{"key":"harv_runicstone","value":"world_s01e01"},{"key":"pg_04_moon_domino_selected","value":"pg_shattered_bay"},{"key":"eg_rockflipping_rock_flip","value":"eg_rockflipping"},{"key":"sanctuary_cityfera","value":"mus_sanctuary_cityfera"},{"key":"pg_01_duel_snap_twofinger","value":"global_pg"},{"key":"vox_kobolds_high_idle_break","value":"vox_kobolds_high_idle_break"},{"key":"pg_01_duel_magic_wall_lp","value":"pg_cityfera"},{"key":"npc_wayfarer_bridge","value":"world_expanse_quest_01"},{"key":"pg_01_duel_snap_onefinger","value":"global_pg"},{"key":"amb_fan_lp","value":"amb_fan_lp"},{"key":"portal_spawn_depart","value":"Global"},{"key":"cg_dye_miss_marguerite_correct","value":"cg_03_doordye"},{"key":"ui_special_action","value":"Global"},{"key":"sfx_five_brodys_spawn","value":"world_expanse_forest"},{"key":"sfx_basic_lamp_on_lp","value":"sfx_basic_lamp"},{"key":"portal_lp","value":"Global"},{"key":"sanctuary_castle","value":"mus_sanctuary_castle"},{"key":"cg_count_down","value":"cg_03_doordye"},{"key":"ui_btn_selfie_video_record","value":"Global"},{"key":"harv_sky_jelly_pop","value":"global_harvest"},{"key":"cooking_pot_lp","value":"cooking_pot_lp"},{"key":"sfx_crow_caw","value":"crowspiracy"},{"key":"ui_edgetab_mainmenu_close","value":"Global"},{"key":"cg_dye_hint_stinger_rightwrong","value":"cg_03_doordye"},{"key":"sfx_typewriter","value":"world_blood_tundra"},{"key":"quest_countdown_timer","value":"toboggan_run"},{"key":"bloodtundra_ocean_bubbles","value":"world_blood_tundra"},{"key":"mus_bloodtundra_title","value":"global_expanse"},{"key":"ui_likes_btn_place_bet","value":"pg_cityfera"},{"key":"quest_unbound_soul_howl","value":"unbound_souls"},{"key":"sfx_pizza_drone","value":"pie_in_the_sky"},{"key":"cg_hex_tile_screen_exit","value":"cg_01_whatthehex"},{"key":"quest_dive_ripples","value":"quest_dive_ripples"},{"key":"quest_marsh_splash","value":"best_sleds"},{"key":"harv_octovenom_move","value":"world_s01e01"},{"key":"cg_m3_btn_puzzle","value":"cg_04_match_3"},{"key":"ui_likes_counter","value":"Global"},{"key":"ui_xp_meter_diamond_whoosh","value":"Global"},{"key":"sfx_basic_candle_on","value":"sfx_basic_candle"},{"key":"ava_dragon_emotes","value":"ava_dragon"},{"key":"mus_qge_picklock","value":"qge_picklock"},{"key":"mus_npc_brodys_race","value":"npc_brodys_race"},{"key":"sfx_ghost_dog_materialize","value":"loyal_spectre"},{"key":"pg_02_fourcrows_card_retract","value":"pg_cityfera"},{"key":"cg_dye_beetle_wings_lp","value":"cg_03_doordye"},{"key":"harv_octovenom_idle","value":"world_s01e01"},{"key":"cg_folly_station_deselect","value":"cg_02_builders_folly"},{"key":"ava_kitsune_emotes","value":"Global"},{"key":"ui_harv_plus_one","value":"Global"},{"key":"ui_creature_switch","value":"Global"},{"key":"ui_btn_report","value":"Global"},{"key":"quest_snowbold_transform","value":"the_lonely_snowbold"},{"key":"quest_seed_toss_grow","value":"sowing_saplings"},{"key":"rs01_vox_queen_delilah","value":"reality_show_01"},{"key":"sanc_axo_ocean_bubbles_lp","value":"axo_ocean_lamp"},{"key":"forestsocial_ambience_main","value":"world_expanse_forest"},{"key":"ui_dialogbox_arrow","value":"Global"},{"key":"cg_hex_tile_shift","value":"cg_01_whatthehex"},{"key":"pg_kino_hand_shuffle","value":"global_pg"},{"key":"s01e01_asparagus","value":"world_s01e01"},{"key":"mus_npc_kobold_brown","value":"mus_npc_kobold_brown"},{"key":"swamp","value":"world_s01e01"},{"key":"sunkenthicket_river_lp","value":"world_sunken_thicket"},{"key":"sanctuary_haunted","value":"mus_sanctuary_haunted"},{"key":"quest_swarm_lp","value":"best_sleds"},{"key":"cg_m3_powerup_dizzy","value":"cg_04_match_3"},{"key":"vox_kobold_white_low","value":"vox_kobold_white_low"},{"key":"amb_wood_creaks","value":"amb_wood_creaks"},{"key":"rs01_aradia_stinger_pleased","value":"reality_show_01"},{"key":"sanc_garden_hose","value":"sanc_garden_hose"},{"key":"sfx_dynamite_explode","value":"lost_shoes"},{"key":"mus_forest_social_title","value":"global_expanse"},{"key":"sfx_stinger_loyal_spectre","value":"loyal_spectre"},{"key":"popup_dialog","value":"Global"},{"key":"tradersport_gulls","value":"world_traders_port"},{"key":"amb_tents","value":"amb_tents"},{"key":"eg_digging_snow_fail","value":"loyal_spectre"},{"key":"quest_snowman_explo","value":"toboggan_run"},{"key":"ui_popup_item_reward","value":"Global"},{"key":"cg_hex_meter_powerup","value":"cg_01_whatthehex"},{"key":"ui_trade_btn_add_radial","value":"Global"},{"key":"cg_dye_hint_stinger_wrong","value":"cg_03_doordye"},{"key":"cityfera_fountain","value":"world_city_fera"},{"key":"cg_folly_tile_rotate","value":"cg_02_builders_folly"},{"key":"ava_phoenix_jump","value":"ava_phoenix"},{"key":"mus_npc_lafayette","value":"mus_npc_lafayette"},{"key":"mus_window_event_log_del","value":"Global"},{"key":"inspirations_terrible_joke_lp","value":"world_expanse_forest"},{"key":"sanc_shower_toggle_on_off","value":"sanc_shower"},{"key":"sanc_pillow_launcher_load","value":"sanc_pillow_launcher"},{"key":"quest_harv_plant_stench_cloud","value":"silent_but_deadly"},{"key":"forest_seagulls_in_flight","value":"chaos_from_above"},{"key":"mus_parlor_kino_game_selection_lp","value":"pg_cityfera"},{"key":"vox_myrefolk_kid","value":"vox_myrefolk_kid"},{"key":"cg_m3_select_bird_slide","value":"cg_04_match_3"},{"key":"vox_captain_vivian","value":"vox_captain_vivian"},{"key":"harv_blooderfly_chirp","value":"global_harvest"},{"key":"vox_twiggles","value":"vox_twiggles"},{"key":"ui_btn_register","value":"login_account_creation"},{"key":"cg_dye_collision_ball_snail","value":"cg_03_doordye"},{"key":"harv_lanternberry_wings","value":"world_s01e01"},{"key":"mus_sky_merchant_shop_orig","value":"mus_sky_merchant"},{"key":"ava_kirin_run_sprint","value":"ava_kirin"},{"key":"ui_btn_inspiration_select_03","value":"Global"},{"key":"fer_harv_plant_amb_LP","value":"global_harvest"},{"key":"cg_folly_box_gears","value":"cg_02_builders_folly"},{"key":"cg_dye_game_over","value":"cg_03_doordye"},{"key":"mus_npc_derpy_kobold_kids","value":"mus_npc_derpy_kobold_kids"},{"key":"sanctuary_haunted_interior","value":"mus_sanctuary_haunted"},{"key":"quest_snowbold_counter_regular","value":"toboggan_run"},{"key":"ui_sanc_btn_side_panel_tab_open","value":"sanctuary_fera"},{"key":"sfx_kite_lp","value":"chaos_from_above"},{"key":"expanse_strider_01","value":"world_expanse_forest"},{"key":"ui_sanc_build_room_complete","value":"sanctuary_ui"},{"key":"cg_dye_splash_screen_lp","value":"cg_03_doordye"},{"key":"cg_hex_tile_special_fall","value":"cg_01_whatthehex"},{"key":"harv_blooderfly_death","value":"global_harvest"},{"key":"ui_sanc_btn_zoom_in","value":"sanctuary_fera"},{"key":"pg_01_duel_dice_selection_keep","value":"pg_cityfera"},{"key":"S01E01_swamp_waterfalls","value":"world_s01e01"},{"key":"cg_dye_collision_ball_jewel","value":"cg_03_doordye"},{"key":"cg_hex_tile_insert_02","value":"cg_01_whatthehex"},{"key":"ui_friend_remove","value":"Global"},{"key":"ui_quest_new_popup","value":"Global"},{"key":"pg_01_duel_dice_single_tabledrop","value":"pg_cityfera"},{"key":"harv_net_swipe_water","value":"world_expanse_quest_01"},{"key":"sfx_mm_fail_stinger","value":"world_s01e01"},{"key":"npc_picken_capture","value":"picken_pick_up"},{"key":"s01e01_lake_02","value":"world_s01e01"},{"key":"eg_rockflipping_rock_flip_final","value":"eg_rockflipping"},{"key":"mus_tradersport_main","value":"world_traders_port"},{"key":"sfx_seagulls_pooping","value":"chaos_from_above"},{"key":"cg_dye_notes_scroll_lp","value":"cg_03_doordye"},{"key":"npc_stinger_hats_big_day","value":"hats_day_out"},{"key":"pg_01_duel_dice_rotate_rise","value":"pg_cityfera"},{"key":"quest_green_spirit_lp","value":"unbound_souls"},{"key":"cg_hex_tile_special_collect_stngr","value":"cg_01_whatthehex"},{"key":"sanc_pillow_launcher_launch","value":"sanc_pillow_launcher"},{"key":"ava_shinigami_jump","value":"ava_shinigami"},{"key":"quest_sfx_cannon_move","value":"cannon_countdown"},{"key":"cg_m3_bird_hatch_regular","value":"cg_04_match_3"},{"key":"ava_phoenix_idle_break_02","value":"ava_phoenix"},{"key":"mus_dyeshop_window","value":"city_fera_dyeshop"},{"key":"vox_myrefolk_high_idle_laugh","value":"vox_myrefolk_high"},{"key":"ui_decal_change","value":"Global"},{"key":"mus_iap_astral_shop","value":"Global"},{"key":"tradersport_balloon_rope","value":"world_traders_port"},{"key":"eg_rockflipping_stinger_03","value":"eg_rockflipping"},{"key":"harv_tab_notification","value":"Global"},{"key":"sanctuary_winter_citadel_interior","value":"mus_sanctuary_winter_citadel"},{"key":"zombold_death","value":"snowman_explo"},{"key":"cg_02_mus_folly_play","value":"cg_02_builders_folly"},{"key":"quest_sfx_coin_well_splash","value":"well_wishes"},{"key":"cg_m3_puzzle_complete","value":"cg_04_match_3"},{"key":"mus_npc_myrefolk","value":"mus_npc_myrefolk"},{"key":"pg_03_m&f_dicecup_reveal","value":"pg_shattered_bay"},{"key":"wpn_spear_return","value":"wpn_spear"},{"key":"ui_xp_meter_diamond_number_increase","value":"Global"},{"key":"ui_xp_harvest_material","value":"Global"},{"key":"ui_inlinetab_customize","value":"Global"},{"key":"pg_04_moon_dealer_token_lp","value":"pg_shattered_bay"},{"key":"cg_hex_splash_screen_lp","value":"cg_01_whatthehex"},{"key":"cg_btn_drop","value":"cg_03_doordye"},{"key":"tradersport_waterfall_sm","value":"world_traders_port"},{"key":"ui_button_close","value":"Global"},{"key":"pg_02_fourcrows_branch_reattach","value":"pg_cityfera"},{"key":"sanc_bubbling_crack","value":"sanc_bubbling_crack"},{"key":"vox_valkeri_low","value":"vox_valkeri_low"},{"key":"sanc_glow_light_toggle_on_off","value":"sanc_glow_light"},{"key":"mus_npc_komodori_snapshot","value":"mus_npc_johannes"},{"key":"holiday_blizzard_lp","value":"holiday_blizzard_lp"},{"key":"ui_decal_edit","value":"Global"},{"key":"qge_picklock_stinger_pickup","value":"qge_picklock"},{"key":"harv_aquarian_redseaweed_idle_lp","value":"world_expanse_forest"},{"key":"sanc_fountain_koi_pond","value":"sanc_fountain_koi_pond"},{"key":"quest_waypoint_lp","value":"global_expanse"},{"key":"door_cottage_open","value":"sanctuary_ui"},{"key":"cg_coin","value":"global_cg"},{"key":"rs01_vox_queen_aradia","value":"reality_show_01"},{"key":"ui_sanc_btn_switch","value":"sanctuary_fera"},{"key":"harv_voidbeetle","value":"world_expanse_forest"},{"key":"ui_btn_new_badge","value":"Global"},{"key":"sanc_garden_hose_toggle_off","value":"sanc_garden_hose"},{"key":"pg_03_m&f_crystaltoken_pickup","value":"pg_shattered_bay"},{"key":"ui_enigma_btn_deselect","value":"Global"},{"key":"mus_npc_walkman","value":"mus_npc_walkman"},{"key":"harv_preymantis_move","value":"world_s01e01"},{"key":"sfx_quest_brodys_race_win","value":"npc_brodys_race"},{"key":"sanc_popcorn","value":"sanc_popcorn"},{"key":"cg_btn_material","value":"global_cg"},{"key":"door_haunted_close","value":"sanctuary_ui"},{"key":"cutscene_treehouse_of_hope","value":"treehouse_of_hope"},{"key":"ui_sanc_btn_shop","value":"sanctuary_fera"},{"key":"sanc_fountain_blood","value":"sanctuary_ui"},{"key":"quest_strange_magic_fail","value":"strange_magic"},{"key":"sanctuary_cityfera_interior","value":"mus_sanctuary_cityfera"},{"key":"vox_myrefolk_low","value":"vox_myrefolk_low"},{"key":"sfx_cutscene_stinger_zombold_invade","value":"snowbold_warfare"},{"key":"eg_rockflipping_stinger_01","value":"eg_rockflipping"},{"key":"harv_creature_death_04","value":"global_harvest"},{"key":"onboarding_quest_complete","value":"onboarding_tutorial"},{"key":"vox_kobolds_low_pushup","value":"vox_kobolds_low_pushup"},{"key":"mus_quest_poofy_poachers_shady","value":"poofy_poachers"},{"key":"cg_hex_pu_bomb_available","value":"cg_01_whatthehex"},{"key":"s01e01_swamp_stingray","value":"global_expanse"},{"key":"mus_npc_brodys_theme","value":"npc_brodys_race"},{"key":"mus_cityfera_clothingshop","value":"city_fera_clothingshop"},{"key":"npc_valkeri_lute","value":"world_traders_port"},{"key":"ui_trade_btn_reject","value":"Global"},{"key":"cutscene_ghost_found","value":"tundra_ghost"},{"key":"ui_btn_striker_purchase","value":"world_traders_port"},{"key":"onboarding_customization_open","value":"Global"},{"key":"sanc_campfire","value":"sanctuary_ui"},{"key":"quest_candy_explo","value":"chasing_away_the_blues"},{"key":"sanc_shower_lp","value":"sanc_shower"},{"key":"harv_ferafly","value":"world_expanse_forest"},{"key":"mus_npc_lute_lp","value":"mus_npc_lute_lp"},{"key":"vox_citizen_posh","value":"vox_citizen_posh"},{"key":"pg_mus_stinger_win","value":"global_pg"},{"key":"wpn_spear_imp_mud_sphere","value":"wpn_spear"},{"key":"ui_sanc_window_decorate","value":"sanctuary_ui"},{"key":"cg_folly_btn_tile_select","value":"cg_02_builders_folly"},{"key":"ui_btn_world_map","value":"Global"},{"key":"ava_shinigami_idle_break_03","value":"ava_shinigami"},{"key":"ui_btn_yes","value":"Global"},{"key":"ava_swim","value":"Global"},{"key":"inspiration_stinger","value":"Global"},{"key":"ui_sanc_btn_rotate","value":"sanctuary_fera"},{"key":"expanse_campfire","value":"global_expanse"},{"key":"cityfera_hot_spring_pool","value":"world_city_fera"},{"key":"ui_toggle_daynight","value":"Global"},{"key":"harv_koi_tab_notification","value":"world_expanse_forest"},{"key":"cityfera_fountain_02","value":"world_city_fera"},{"key":"cg_04_mus_match3","value":"cg_04_match_3"},{"key":"mus_cindernoct_shatteredbay","value":"world_traders_port"},{"key":"qge_picklock_stab_05","value":"qge_picklock"},{"key":"ava_fae_breath_run","value":"ava_fae"},{"key":"cg_folly_btn_speed_normal","value":"cg_02_builders_folly"},{"key":"cg_hex_icon_respawn","value":"cg_01_whatthehex"},{"key":"vox_shoes","value":"vox_shoes"},{"key":"ava_gliding_updraft_exit","value":"gliding_updraft_enter_exit"},{"key":"mus_forest_social_main","value":"world_expanse_forest"},{"key":"ava_wings_movement_light","value":"ava_wings_movement_light"},{"key":"quest_toboggan_imp_building","value":"toboggan_run"},{"key":"mus_frostfete_sunkenthicket","value":"world_sunken_thicket"},{"key":"mus_quest_poofy_poachers_sad","value":"poofy_poachers"},{"key":"ui_btn_shop_item_select","value":"Global"},{"key":"ui_btn_battle_pass_select","value":"Global"},{"key":"quest_ghost_lp","value":"tundra_ghost"},{"key":"cg_folly_stinger_scorebar","value":"cg_02_builders_folly"},{"key":"ava_werewolf_emotes","value":"ava_werewolf"},{"key":"cg_btn_generic_back_arrow","value":"global_cg"},{"key":"cg_folly_stinger_delivered_01","value":"cg_02_builders_folly"},{"key":"quest_harv_plant_stench_lp","value":"silent_but_deadly"},{"key":"sanc_pillow_launch_explode","value":"sanc_pillow_launcher"},{"key":"wpn_spear_lp","value":"wpn_spear"},{"key":"quest_rock_float","value":"magnificent_cleanup"},{"key":"vox_statue","value":"vox_statue"},{"key":"cityfera_clock_gears","value":"world_city_fera"},{"key":"pg_01_duel_dice_rotate_lp","value":"pg_cityfera"},{"key":"sfx_stingray_swamp_water_splash","value":"world_s01e01"},{"key":"sfx_basic_lamp_off","value":"sfx_basic_lamp"},{"key":"sanctuary_frost_fete","value":"mus_sanctuary_frost_fete"},{"key":"forestsocial_beetle_wings_lp","value":"world_expanse_forest"},{"key":"mus_captain_cluck_geyser_tension","value":"captain_cluck"},{"key":"cg_folly_btn_speed_fast_forward","value":"cg_02_builders_folly"},{"key":"amb_cindernoct_vermin","value":"amb_cindernoct_vermin"},{"key":"pg_02_fourcrows_branch_move","value":"pg_cityfera"},{"key":"ava_phoenix_emotes_test","value":"ava_phoenix"},{"key":"mus_trading_lp","value":"Global"},{"key":"ava_senri_breath_run","value":"ava_senri"},{"key":"vox_kobolds_low_yoga","value":"vox_kobolds_low_yoga"},{"key":"pg_02_fourcrows_deal_card","value":"pg_cityfera"},{"key":"ui_delete_option","value":"Global"},{"key":"bloodtundra_scary_stingers","value":"world_blood_tundra"},{"key":"npc_mm_death","value":"wpn_spear"},{"key":"vox_valkeri_icarus","value":"vox_valkeri_icarus"},{"key":"mus_shop_furniture","value":"sanctuary_ui"},{"key":"ui_dye_crafted","value":"Global"},{"key":"cg_folly_btn_broom","value":"cg_02_builders_folly"},{"key":"ava_gliding_updraft_rune_lp","value":"ava_gliding_updraft_wind"},{"key":"sanc_carnivorous_larry_idle","value":"sanc_carnivorous_larry"},{"key":"fer_decreeboard_raise","value":"Global"},{"key":"mus_iap_shop","value":"Global"},{"key":"sanctuary_frost_fete_interior","value":"mus_sanctuary_frost_fete"},{"key":"harv_rubyfish_idle","value":"Global"},{"key":"forestsocial_lake","value":"world_expanse_forest"},{"key":"ui_customization_night","value":"Global"},{"key":"sanctuary_voyager","value":"mus_sanctuary_voyager"},{"key":"mus_window_event_log","value":"Global"},{"key":"cg_dye_collision_ball_eye","value":"cg_03_doordye"},{"key":"mus_s01e01_main_2d","value":"world_s01e01"},{"key":"tradersport_water_safetyline","value":"world_traders_port"},{"key":"cg_hex_pu_bomb_place","value":"cg_01_whatthehex"},{"key":"wpn_spear_launch","value":"wpn_spear"},{"key":"ui_sanc_btn_decorate_deselect","value":"sanctuary_fera"},{"key":"ui_appform_login","value":"login_account_creation"},{"key":"ui_btn_avatarselect","value":"Global"},{"key":"cg_btn_next","value":"global_cg"},{"key":"harv_iceplatelet_lp","value":"world_blood_tundra"},{"key":"sfx_statue_pipe_unclogged","value":"fountain_fix"},{"key":"ui_quest_tab_close","value":"Global"},{"key":"pg_02_fourcrows_gameboard_roll_up","value":"global_pg"},{"key":"ava_shinigami_emotes","value":"ava_shinigami"},{"key":"cutscene_camera_wonder","value":"global_cutscenes"},{"key":"harv_creature_death_03","value":"global_harvest"},{"key":"popup_secret_place","value":"Global"},{"key":"harv_creature_death_05","value":"global_harvest"},{"key":"sanctuary_chateau","value":"mus_sanctuary_chateau"},{"key":"cg_m3_bird_combo_rainbow","value":"cg_04_match_3"},{"key":"cityfera_wind","value":"world_city_fera"},{"key":"mus_frostfete_cityfera","value":"world_city_fera"},{"key":"cg_dye_miss_marguerite_wrong","value":"cg_03_doordye"},{"key":"npc_mm_mud_projectile_approach","value":"world_s01e01"},{"key":"portal_arrival_depart","value":"world_city_fera"},{"key":"vox_kobold_white_high","value":"vox_kobold_white_high"},{"key":"sfx_ghost_dog_bark_multiple","value":"loyal_spectre"},{"key":"pg_01_duel_magic_wall_disappear","value":"pg_cityfera"},{"key":"eg_01_mus_runestone","value":"world_expanse_forest"},{"key":"tradersport_crystal_sm","value":"world_traders_port"},{"key":"ui_uncrafting_btn_deselect","value":"Global"},{"key":"ui_stinger_success","value":"lost_shoes"},{"key":"quest_babies_cry","value":"chasing_away_the_blues"},{"key":"cg_hex_tile_select","value":"cg_01_whatthehex"},{"key":"eg_digging_snow","value":"eg_dig_up"},{"key":"sanctuary_voyager_interior","value":"mus_sanctuary_voyager"},{"key":"cg_tutorial_popup","value":"global_cg"},{"key":"quest_wood_creaks","value":"global_expanse"},{"key":"ui_map_box_select","value":"Global"},{"key":"cg_hex_tile_special_collect","value":"cg_01_whatthehex"},{"key":"sfx_ghost_dog_bark","value":"loyal_spectre"},{"key":"rs01_aradia_stinger_love","value":"reality_show_01"},{"key":"harv_cinderfish_move","value":"world_expanse_forest"},{"key":"cg_folly_twiggle_cheer_03","value":"cg_02_builders_folly"},{"key":"portal_arrival","value":"city_fera_lounge"},{"key":"pg_02_fourcrows_card_placed","value":"pg_cityfera"},{"key":"sfx_keys_jangle","value":"vox_komodori_shady"},{"key":"mus_npc_valkeri_messenger","value":"mus_npc_valkeri_messenger"},{"key":"mus_sticky_situation_danger","value":"world_s01e01"},{"key":"ui_btn_inspiration_deselect","value":"Global"},{"key":"bloodtundra_lake","value":"world_blood_tundra"},{"key":"npc_picken_hickup","value":"npc_picken_idle"},{"key":"npc_mm_alert","value":"world_s01e01"},{"key":"pg_03_m&f_crystaltoken_placed","value":"pg_shattered_bay"},{"key":"quest_collected_bones","value":"world_blood_tundra"},{"key":"onboarding_clock_gears","value":"onboarding_tutorial"},{"key":"ui_xp_meter_glow","value":"Global"},{"key":"sanc_plasma_light_lp","value":"sanc_plasma_light"},{"key":"ava_wings_fairy","value":"ava_wings_soft"},{"key":"cg_hex_pu_bomb_select","value":"cg_01_whatthehex"},{"key":"pg_01_duel_gameboard_rollin","value":"global_pg"},{"key":"cg_m3_powerup_hatch","value":"cg_04_match_3"},{"key":"qge_chest_lid_close","value":"qge_picklock"},{"key":"ui_black_market_shop_btn_craft","value":"Global"},{"key":"inspirations_albatross","value":"world_expanse_forest"},{"key":"quest_sfx_twiggle_scream","value":"cannon_countdown"},{"key":"cg_dye_btn_mix","value":"cg_03_doordye"},{"key":"pg_01_duel_dice_pickup_slide","value":"pg_cityfera"},{"key":"harv_vegetation_harvested","value":"global_harvest"},{"key":"sanctuary_woodland_cottage","value":"mus_sanctuary_woodland_cottage"},{"key":"pg_02_fourcrows_flap_vanish","value":"pg_cityfera"},{"key":"harv_tool_paw","value":"Global"},{"key":"cg_folly_station_cooking","value":"cg_02_builders_folly"},{"key":"mus_npc_citizen","value":"mus_npc_citizen"},{"key":"sfx_crafting_eureka","value":"city_fera_clothingshop"},{"key":"ui_sanc_btn_zoom_out","value":"sanctuary_fera"},{"key":"vox_queen_aradia","value":"reality_show_01"},{"key":"quest_crate_unlock","value":"poofy_poachers"},{"key":"harv_tool_bash_fist","value":"Global"},{"key":"dyeshop_beetle_blue_wings_lp","value":"city_fera_dyeshop"},{"key":"sanc_tub_bubbles_lp","value":"sanc_tub_bubbles_lp"},{"key":"mus_sky_merchant_shop","value":"mus_sky_merchant"},{"key":"mus_queens_reality_show_01","value":"reality_show_01"},{"key":"quest_waypoint_water_lp","value":"Global"},{"key":"ava_phoenix_idle_break_03","value":"ava_phoenix"},{"key":"forest_quest_gulls","value":"chaos_from_above"},{"key":"s01e01_lake_01","value":"world_s01e01"},{"key":"cg_hex_tile_board_lift","value":"cg_01_whatthehex"},{"key":"ava_werewolf_jump","value":"ava_werewolf"},{"key":"mus_npc_kobold_blood","value":"mus_npc_kobold_blood"},{"key":"harv_net_swipe_ground","value":"world_expanse_quest_01"},{"key":"portal_spawn_arrival","value":"Global"},{"key":"fer_decreeboard_lower","value":"Global"},{"key":"mus_parlor_kino_lp","value":"pg_cityfera"},{"key":"sanc_beehive","value":"sanc_beehive"},{"key":"cg_02_mus_folly_setup","value":"cg_02_builders_folly"},{"key":"pg_01_duel_atk_ctr_app_disap","value":"pg_cityfera"},{"key":"ava_fae_jump","value":"ava_fae"},{"key":"qge_picklock_lock","value":"qge_picklock"},{"key":"ava_senri_jump","value":"ava_senri"},{"key":"cg_dye_miss_marguerite_some","value":"cg_03_doordye"},{"key":"harv_preymantis_idle","value":"world_s01e01"},{"key":"quest_toboggan_imp_tree","value":"toboggan_run"},{"key":"harv_spider_vein_harvesting","value":"global_harvest"},{"key":"rs01_camera_zoom_out","value":"reality_show_01"},{"key":"sfx_amb_pants","value":"sfx_amb_pants"},{"key":"npc_valkeri_drum","value":"Global"},{"key":"pg_01_duel_dice_group_pickup_roll","value":"pg_cityfera"},{"key":"cg_dye_discard_ingredient","value":"cg_03_doordye"},{"key":"ui_edgetab_mainmenu_open","value":"Global"},{"key":"cg_folly_btn_station_select","value":"cg_02_builders_folly"},{"key":"mus_dry_or_die_tension","value":"dry_or_die"},{"key":"sanc_fountain_spring_clover","value":"sanc_fountain_spring_clover"},{"key":"ui_decal_delete","value":"Global"},{"key":"tradersport_buoys","value":"world_traders_port"},{"key":"cg_hex_meter_flora","value":"cg_01_whatthehex"},{"key":"sfx_dry_or_die_fail_stinger","value":"dry_or_die"},{"key":"quest_spring_fountain_lp","value":"seasonal_tea"},{"key":"mus_quest_poofy_sad_cutscene","value":"poofy_poachers"},{"key":"quest_whistle","value":"poofy_poachers"},{"key":"vox_seraphs_karen","value":"vox_seraphs_karen"},{"key":"ui_btn_battle_pass","value":"Global"},{"key":"eg_rockflipping_shatter_stinger","value":"eg_rockflipping"},{"key":"ui_emoticon_popup","value":"Global"},{"key":"ui_inspiration_found_stinger","value":"Global"},{"key":"ava_phoenix_breath_idle","value":"ava_phoenix"},{"key":"cg_m3_game_win","value":"cg_04_match_3"},{"key":"ui_ingredient_02","value":"Global"},{"key":"ui_btn_collect_all","value":"Global"},{"key":"ui_btn_radial","value":"Global"},{"key":"mus_wayfarer_bridge","value":"world_expanse_quest_01"},{"key":"vox_recollector","value":"vox_recollector"},{"key":"quest_crowspiracy_seeds_toss","value":"crowspiracy"},{"key":"ui_btn_save_look","value":"Global"},{"key":"quest_item_remembered_stinger","value":"the_lonely_snowbold"},{"key":"eg_rockflipping_stinger_02","value":"eg_rockflipping"},{"key":"mus_npc_beast_statue","value":"mus_npc_beast_statue"},{"key":"sanc_cauldron","value":"sanc_cauldron"},{"key":"ava_wing_medium_flap","value":"Global"},{"key":"bloodtundra_ocean","value":"world_blood_tundra"},{"key":"ui_likes_btn_max","value":"Global"},{"key":"pg_04_moon_dominos_bag_return","value":"pg_shattered_bay"},{"key":"ava_kirin_breath_run","value":"ava_kirin"},{"key":"ui_minus","value":"Global"},{"key":"onboarding_lights_on","value":"onboarding_tutorial"},{"key":"harv_crystalback_beetle","value":"world_s01e01"},{"key":"mus_quest_follow_footsteps_theme","value":"twiggle_p_i"},{"key":"ui_btn_sanctuary","value":"Global"},{"key":"quest_comic_boom_effect","value":"finders_keepers"},{"key":"amb_stingray_large_passby","value":"world_expanse_forest"},{"key":"sanc_plasma_light_toggle_on_off","value":"sanc_plasma_light"},{"key":"bloodtundra_blood_stalks","value":"world_blood_tundra"},{"key":"door_haunted_open","value":"sanctuary_ui"},{"key":"ui_colortabs_fancyscroll","value":"Global"},{"key":"ui_private_message_send","value":"Global"},{"key":"vox_first_mate","value":"captain_cluck"},{"key":"cg_m3_stinger_bird_flyer","value":"cg_04_match_3"},{"key":"pg_01_duel_gameboard_rollout","value":"pg_cityfera"},{"key":"snowman_explo","value":"snowman_explo"},{"key":"cutscene_camera_short","value":"global_cutscenes"},{"key":"sanc_thunder","value":"mus_sanctuary_voyager"},{"key":"ui_sanc_btn_exterior","value":"sanctuary_fera"},{"key":"ui_furniture_shop_btn_craft","value":"Global"},{"key":"qge_picklock_stab_03","value":"qge_picklock"},{"key":"cityfera_hot_spring_waterfall","value":"world_city_fera"},{"key":"cg_folly_station_hammer","value":"cg_02_builders_folly"},{"key":"ui_btn_logout","value":"Global"},{"key":"qge_window_close","value":"qge_picklock"},{"key":"quest_magic_dust_lp","value":"quest_magic_staff_lp"},{"key":"glide_initiate","value":"ava_glide_lp"},{"key":"sanctuary_sunken_thicket","value":"mus_sanctuary_sunken_thicket"},{"key":"cg_folly_material_wiggle","value":"cg_02_builders_folly"},{"key":"mus_npc_serial_chiller","value":"mus_npc_serial_chiller"},{"key":"sanctuary_shattered_bay_interior","value":"mus_sanctuary_shattered_bay"},{"key":"sanctuary_chateau_interior","value":"mus_sanctuary_chateau"},{"key":"qge_picklock_ring_treasure","value":"qge_picklock"},{"key":"mus_npc_myrefolk_well_wishes","value":"well_wishes"},{"key":"sanc_treadmill","value":"sanc_treadmill"},{"key":"mus_wayfarer_intro","value":"world_expanse_quest_01"},{"key":"qge_picklock_ring_fade","value":"qge_picklock"},{"key":"cutscene_camera_playful","value":"global_cutscenes"},{"key":"ui_trade_btn_item_remove","value":"Global"},{"key":"pg_04_moon_dealer_token_stop","value":"pg_shattered_bay"},{"key":"cityfera_hot_spring_large_pool","value":"world_city_fera"},{"key":"mus_window_notification_quest_log","value":"Global"},{"key":"mus_shop_sky_merchant","value":"mus_sky_merchant"},{"key":"vox_poofy","value":"poofy_poachers"},{"key":"mus_npc_kino","value":"mus_npc_kino"},{"key":"crystal_sm","value":"crystal_sm"},{"key":"qge_picklock_stinger_fail","value":"qge_picklock"},{"key":"ava_kitsune_breath_idle","value":"Global"},{"key":"cg_hex_game_over_stngr","value":"cg_01_whatthehex"},{"key":"harv_ruinclam_idle","value":"world_expanse_forest"},{"key":"cg_folly_btn_clear_board","value":"cg_02_builders_folly"},{"key":"ui_charm_slot","value":"Global"},{"key":"cg_m3_stinger_bird_peacock","value":"cg_04_match_3"},{"key":"ui_popup_secret_crafting_item","value":"Global"},{"key":"ui_btn_selfie_video_stop","value":"Global"},{"key":"crystal_lrge","value":"crystal_lrge"},{"key":"qge_picklock_shatter","value":"qge_picklock"},{"key":"mus_hats_big_day_montage","value":"hats_day_out"},{"key":"cg_dye_wheel_tap","value":"cg_03_doordye"},{"key":"quest_strange_magic_success","value":"strange_magic"},{"key":"cg_point_counter","value":"cg_03_doordye"},{"key":"quest_cannon_twiggle_found_dirt","value":"cannon_countdown"},{"key":"mus_daily_toboggan_run","value":"world_blood_tundra"},{"key":"npc_mm_mud_splatter_miss","value":"world_s01e01"},{"key":"bloodtundra_gusts","value":"world_blood_tundra"},{"key":"ava_dragon_jump","value":"ava_dragon"},{"key":"ui_ingredient_01","value":"Global"},{"key":"boundary_death","value":"Global"},{"key":"vox_twiggles_idle_break","value":"vox_twiggles_idle_break"},{"key":"ava_gliding_updraft_wind","value":"ava_gliding_updraft_wind"},{"key":"cg_dye_wheel_drag_lp","value":"cg_03_doordye"},{"key":"mus_forest_social_main_2d","value":"world_expanse_forest"},{"key":"S01E01_swamp_waterfall_pools","value":"world_s01e01"},{"key":"cg_folly_btn_reward","value":"cg_02_builders_folly"},{"key":"ui_btn_shop_item_deselect","value":"Global"},{"key":"mus_loyal_spectre","value":"loyal_spectre"},{"key":"mus_cityfera_dyeshop","value":"city_fera_dyeshop"},{"key":"popup_no_access","value":"Global"},{"key":"quest_poofy_poachers_inspection","value":"poofy_poachers"},{"key":"harv_spider_vein_vox","value":"global_harvest"},{"key":"sfx_magic_wand_lp","value":"magnificent_cleanup"},{"key":"npc_mm_mud_splatter_hit","value":"world_s01e01"},{"key":"npc_picken_idle","value":"npc_picken_idle"},{"key":"sfx_inspiration_candle_on","value":"Global"},{"key":"quest_toboggan_imp_rock","value":"toboggan_run"},{"key":"harv_wet_weed","value":"world_expanse_quest_01"},{"key":"harv_ruinclam_move","value":"world_expanse_forest"},{"key":"ava_werewolf_breath_run","value":"ava_werewolf"},{"key":"ui_btn_astral_select","value":"Global"},{"key":"cg_dye_collision_ball_spike","value":"cg_03_doordye"},{"key":"cutscene_ghost_grave_enter","value":"tundra_ghost"},{"key":"tradersport_boardwalk","value":"world_traders_port"},{"key":"npc_mm_spot_player","value":"world_s01e01"},{"key":"portal_depart","value":"city_fera_lounge"},{"key":"sfx_ghost_dog_whimper","value":"loyal_spectre"},{"key":"cutscene_camera_fade_black","value":"global_cutscenes"},{"key":"vox_kino","value":"vox_kino"},{"key":"cg_dye_hint_stinger_correct","value":"cg_03_doordye"},{"key":"cg_stinger_scorebar","value":"cg_03_doordye"},{"key":"harv_beetle_collect","value":"treehouse_of_hope"},{"key":"ava_shinigami_flight_lp","value":"ava_shinigami"},{"key":"cg_hex_tile_special_place","value":"cg_01_whatthehex"},{"key":"cutscene_ghost_grave_glide","value":"tundra_ghost"},{"key":"vox_captain_cluck","value":"captain_cluck"},{"key":"ui_sanc_btn_remove_all","value":"sanctuary_fera"},{"key":"ava_phoenix_emotes","value":"ava_phoenix"},{"key":"sanc_fountain_spout","value":"sanctuary_ui"},{"key":"mus_quest_toboggan_lp","value":"toboggan_run"},{"key":"sunken_thicket_ambience_main","value":"world_sunken_thicket"},{"key":"sanctuary_rose_house","value":"mus_sanctuary_rose_house"},{"key":"floating_rocks_move","value":"global_expanse"},{"key":"vox_kobold_kid","value":"vox_kobold_kid"},{"key":"ui_trade_popup","value":"Global"},{"key":"sanc_haunted_thunder","value":"mus_sanctuary_haunted"},{"key":"amb_firepit_lp","value":"amb_firepit_lp"},{"key":"ui_btn_inspiration_select_01","value":"Global"},{"key":"cg_btn_okay","value":"global_cg"},{"key":"ui_btn_selfie_gallerie","value":"Global"},{"key":"sunkenthicket_lake_waves_lp","value":"world_sunken_thicket"},{"key":"ui_map_box_rollover","value":"Global"},{"key":"cg_m3_bird_pop","value":"cg_04_match_3"},{"key":"pg_04_moon_token_spawn","value":"pg_shattered_bay"},{"key":"sanc_item_select","value":"Global"},{"key":"mus_npc_kino_sunkenthicket","value":"world_sunken_thicket"},{"key":"vox_vermin_move","value":"vox_vermin"},{"key":"harv_blooddew_back_idle","value":"world_blood_tundra"},{"key":"sfx_surprise_skull_ghost","value":"sfx_surprise_ghost_skull"},{"key":"harv_death_blooddew_back","value":"world_blood_tundra"},{"key":"harv_purelight_flower","value":"world_s01e01"},{"key":"sfx_geyser_lp","value":"captain_cluck"},{"key":"quest_pumpkin_regular_explo","value":"garden_of_evil"},{"key":"eg_digging_dirt","value":"eg_dig_up"},{"key":"vox_kobolds_high","value":"vox_kobolds_high"},{"key":"ava_wings_jagged","value":"ava_wings_jagged"},{"key":"sfx_ghost_dog_howl","value":"loyal_spectre"},{"key":"ui_accessory_equip","value":"Global"},{"key":"vox_miss_marguerite","value":"vox_miss_marguerite"},{"key":"qge_picklock_stab_01","value":"qge_picklock"},{"key":"pg_01_duel_clap","value":"pg_cityfera"},{"key":"ui_dye_used","value":"Global"},{"key":"mus_npc_magician","value":"mus_npc_magician"},{"key":"ava_gliding_updraft_enter","value":"gliding_updraft_enter_exit"},{"key":"onboarding_cutscene_intro","value":"onboarding_tutorial"},{"key":"cg_folly_splash_screen_lp","value":"cg_02_builders_folly"},{"key":"quest_item_collect_1st_time","value":"Global"},{"key":"cg_dye_cauldron_lp","value":"cg_03_doordye"},{"key":"expanse_fountain","value":"global_expanse"},{"key":"npc_stinger_hats_big_day_danger","value":"hats_day_out"},{"key":"pg_02_fourcrows_amb_stab","value":"pg_cityfera"},{"key":"sanc_vintage_sink_lp","value":"sanc_vintage_sink_lp"},{"key":"ui_map_zoom_in","value":"Global"},{"key":"ava_fae_breath_idle","value":"ava_fae"},{"key":"quest_ghost_dig_site_lp","value":"global_expanse"},{"key":"cg_hex_tile_fall","value":"cg_01_whatthehex"},{"key":"cityfera_hot_spring_waterfall_01","value":"world_city_fera"},{"key":"mus_npc_brody_bro_fu","value":"mus_npc_brody_bro_fu"},{"key":"pg_02_fourcrows_crow_spawn","value":"pg_cityfera"},{"key":"quest_toboggan_victory","value":"toboggan_run"},{"key":"ui_avatar_switch_spawn","value":"Global"},{"key":"ui_btn_royal_boutique_purchase","value":"Global"},{"key":"onboarding_player_spark_burst","value":"onboarding_tutorial"},{"key":"sunken_thicket_bubbles","value":"world_sunken_thicket"},{"key":"npc_latchkey_uncrafting_machine","value":"world_sunken_thicket"},{"key":"sanc_fountain_shishi_odoshi","value":"sanc_fountain_shishi_odoshi"},{"key":"ui_toggle_show_hide","value":"Global"},{"key":"quest_you_got_an_item","value":"Global"},{"key":"quest_magic_poof","value":"strange_magic"},{"key":"sunkenthicket_waterfall_sm","value":"world_sunken_thicket"},{"key":"sfx_orb_stone_lp","value":"global_expanse"},{"key":"vox_miss_marguerite_crafting","value":"vox_miss_marguerite"},{"key":"ui_creature_choose","value":"Global"},{"key":"harv_sky_chest_collect","value":"global_harvest"},{"key":"vox_kobolds_low_run","value":"vox_kobolds_low_run"},{"key":"cg_btn_cancel","value":"global_cg"},{"key":"wpn_light_spear_pickup","value":"wpn_spear"},{"key":"amb_frost_fete_snowpuff_move","value":"world_city_fera"},{"key":"harv_sky_jelly_idle","value":"global_harvest"},{"key":"sanctuary_sunken_thicket_interior","value":"mus_sanctuary_sunken_thicket"},{"key":"sanctuary_cottage","value":"mus_sanctuary_cottage"},{"key":"sanc_epic_kino_figurine","value":"sanc_epic_kino_figurine"},{"key":"harv_spider_vein_death","value":"global_harvest"},{"key":"sanc_fire_toggle_on_off","value":"sanc_fire_toggle_on_off"},{"key":"mus_wayfarer_uncertain","value":"world_expanse_quest_01"},{"key":"mus_decree_board","value":"mus_decree_board"},{"key":"pg_kino_restinghands_clear_table","value":"global_pg"},{"key":"ava_shinigami_breath_idle","value":"ava_shinigami"},{"key":"mus_quest_johannes_song","value":"poofy_poachers"},{"key":"wpn_spear_imp","value":"wpn_spear"},{"key":"amb_cooking_fish","value":"world_s01e01"},{"key":"vox_citizen_kid","value":"vox_citizen_kid"},{"key":"mus_qge_picklock_silver","value":"qge_picklock"},{"key":"sfx_mm_quest_09_stab","value":"world_s01e01"},{"key":"pg_04_moon_dealer_token_start","value":"pg_shattered_bay"},{"key":"sfx_nettlebane_candle_on","value":"sanctuary_ui"},{"key":"cityfera_hot_spring_wind","value":"world_city_fera"},{"key":"ui_sanc_btn_side_panel_tab_close","value":"sanctuary_fera"},{"key":"mus_daily_spear_it_tension","value":"mus_daily_spear_it"},{"key":"sanc_birdcage","value":"sanc_birdcage"},{"key":"expanse_wind","value":"world_s01e01"},{"key":"ui_stinger_star_purchase","value":"Global"},{"key":"npc_poof_happy","value":"poofy_poachers"},{"key":"npc_poof_scared","value":"poofy_poachers"},{"key":"mus_tradersport_title","value":"world_traders_port"},{"key":"sfx_dynamite_pickup","value":"lost_shoes"},{"key":"glide_updraft_launch_avatar","value":"ava_gliding_updraft_whoosh"},{"key":"sfx_player_failed_stinger","value":"global_expanse"},{"key":"sanc_mirror_haunted","value":"sanc_mirror_haunted"},{"key":"ui_accessory_remove","value":"Global"},{"key":"forestsocial_bells","value":"world_expanse_forest"},{"key":"amb_stingray_large_wing","value":"world_expanse_forest"},{"key":"cg_btn_tap_to_continue","value":"global_cg"},{"key":"rs01_vox_queen_stingers_aradia","value":"reality_show_01"},{"key":"mus_sunken_thicket_title","value":"world_sunken_thicket"},{"key":"ava_dragon_flight_lp","value":"ava_dragon"},{"key":"sfx_toboggan_sled_lp","value":"sfx_sled_lp"},{"key":"mus_cityfera_title","value":"world_city_fera"},{"key":"S01E01_swamp_02","value":"world_s01e01"},{"key":"sanc_blender_with_fruits","value":"sanc_blender_with_fruits"},{"key":"dyeshop_cauldron","value":"dyeshop_cauldron"},{"key":"sanc_fountain","value":"sanctuary_ui"},{"key":"pg_01_duel_btn_attack","value":"pg_cityfera"},{"key":"ui_btn_save_look_02","value":"Global"},{"key":"harv_tool_hammer","value":"Global"},{"key":"mus_npc_kino_tradersport","value":"world_traders_port"},{"key":"ui_dye_select","value":"Global"},{"key":"mus_daily_spear_it_danger","value":"mus_daily_spear_it"},{"key":"npc_mm_mud_throw","value":"world_s01e01"},{"key":"ui_plus","value":"Global"},{"key":"sanctuary_castle_interior","value":"mus_sanctuary_castle"},{"key":"pg_02_fourcrows_tree_materialize","value":"pg_cityfera"},{"key":"ui_map_icon_anim","value":"Global"},{"key":"amb_wood_creaks_muffled","value":"amb_wood_creaks"},{"key":"mus_season_pass_challenge","value":"Global"},{"key":"ui_accessory_select","value":"Global"},{"key":"npc_wayfarer_rise","value":"world_expanse_quest_01"},{"key":"ava_fae_sleep_exit","value":"ava_fae"},{"key":"ava_wings_small","value":"ava_wings_small"},{"key":"cg_dye_cauldron_ball_splash","value":"cg_03_doordye"},{"key":"cg_m3_stinger_bird_bomb","value":"cg_04_match_3"},{"key":"amb_stingray_large_passby_vo","value":"world_expanse_forest"},{"key":"s01e01_tents","value":"world_s01e01"},{"key":"sanc_spring_windchime_lp","value":"sanc_spring_windchime_lp"},{"key":"vox_valkeri_messenger","value":"vox_valkeri_messenger"},{"key":"harv_sky_jelly_hit","value":"global_harvest"},{"key":"ui_btn_arrow","value":"Global"},{"key":"qge_picklock_stab_02","value":"qge_picklock"},{"key":"mus_bloodtundra_ambient","value":"world_blood_tundra"},{"key":"quest_snowbold_moan","value":"toboggan_run"},{"key":"ui_btn_iap_crown","value":"Global"},{"key":"npc_whisp_zoom","value":"world_expanse_quest_01"},{"key":"harv_creature_death_02","value":"global_harvest"},{"key":"inspiration_combination_success","value":"Global"},{"key":"ava_jackalope_jump","value":"ava_jackalope"},{"key":"sanc_treadmill_toggle_on_off","value":"sanc_treadmill"},{"key":"pg_kino_finger_tap","value":"global_pg"},{"key":"mus_quest_novel_romance","value":"a_novel_romance"},{"key":"cg_folly_station_sew","value":"cg_02_builders_folly"},{"key":"quest_ghost_zoom","value":"tundra_ghost"},{"key":"mus_npc_captain_cluck","value":"mus_npc_captain_cluck"},{"key":"ava_kitsune_jump","value":"Global"},{"key":"vox_komodori_teeter","value":"vox_komodori_teeter"},{"key":"onboarding_highlighter","value":"onboarding_tutorial"},{"key":"ava_phoenix_flight_lp","value":"ava_phoenix"},{"key":"ui_mainmenubar_btnpanel","value":"Global"},{"key":"pg_03_m&f_cup_dice_wiggle","value":"pg_shattered_bay"},{"key":"pg_04_moon_crystal_token_lp","value":"pg_shattered_bay"},{"key":"ui_xp_meter_diamond_multiple","value":"Global"},{"key":"pg_02_fourcrows_branch_snap","value":"pg_cityfera"},{"key":"pg_01_duel_magic_wall_appear","value":"pg_cityfera"},{"key":"npc_kino_magic","value":"npc_kino_magic"},{"key":"sanc_aquarium_bubbles_lp","value":"sanc_aquarium_bubbles_lp"},{"key":"harv_venusdandy_idle_lp","value":"world_expanse_forest"},{"key":"sunkenthicket_lake","value":"world_sunken_thicket"},{"key":"vox_sergeant_hawke","value":"vox_sergeant_hawke"},{"key":"ui_sanc_btn_item_x","value":"sanctuary_fera"},{"key":"forestsocial_wind","value":"world_expanse_forest"},{"key":"sanctuary_winter_citadel","value":"mus_sanctuary_winter_citadel"},{"key":"cg_m3_select_bird_no_match","value":"cg_04_match_3"},{"key":"cg_folly_btn_tile_clear","value":"cg_02_builders_folly"},{"key":"ui_trade_btn_ready","value":"Global"},{"key":"mus_quest_witches_broom_lp","value":"hocus_pocus"},{"key":"sanc_sunken_thicket_thunder","value":"sanctuary_ui"},{"key":"mus_bloodtundra_main","value":"world_blood_tundra"},{"key":"cg_dye_collision_ball_worm","value":"cg_03_doordye"},{"key":"vox_valkeri_high","value":"vox_valkeri_high"},{"key":"harv_hanging_bells","value":"world_s01e01"},{"key":"ava_jackalope_breath_run","value":"ava_jackalope"},{"key":"tradersport_tarps","value":"world_traders_port"},{"key":"vox_queen_delilah","value":"reality_show_01"},{"key":"mus_swamp_stickysituation_main","value":"world_s01e01"},{"key":"ui_btn_trade","value":"Global"},{"key":"ui_btn_battle_pass_my_challenges","value":"Global"},{"key":"pg_03_m&f_dice_roll","value":"pg_shattered_bay"},{"key":"quest_321_go","value":"global_expanse"},{"key":"mus_bloodtundra_secret_area","value":"world_blood_tundra"},{"key":"mus_tutorial","value":"onboarding_tutorial"},{"key":"sfx_ghost_dog_dematerialize","value":"loyal_spectre"},{"key":"pg_mus_stinger_fail","value":"global_pg"},{"key":"cg_folly_station_placed","value":"cg_02_builders_folly"},{"key":"cg_folly_station_saw","value":"cg_02_builders_folly"},{"key":"npc_twiggle_flame","value":"Global"},{"key":"ui_e_complete","value":"Global"},{"key":"sanc_glow_light_lp","value":"sanc_glow_light"},{"key":"mus_s01e01_main","value":"world_s01e01"},{"key":"pg_04_moon_crystal_token_stop","value":"pg_shattered_bay"},{"key":"harv_twinkling_twine","value":"global_expanse"},{"key":"tradersport_ocean_deep_lp","value":"world_traders_port"},{"key":"mus_quest_poofy_sad","value":"poofy_poachers"},{"key":"ui_dye_btn_craft_meter","value":"Global"},{"key":"mus_frostfete_shatteredbay","value":"world_traders_port"},{"key":"sfx_cutscene_pizza_parkour","value":"pizza_parkour"},{"key":"ui_btn_selfie_click","value":"Global"},{"key":"cg_m3_bird_combo","value":"cg_04_match_3"}]}